MysqlXingnengDiaoyouYuJiagoushejiJesselzj/README.md
MysqlXingnengDiaoyouYuJiagoushejiJesselzj/__init__.py
MysqlXingnengDiaoyouYuJiagoushejiJesselzj/__main__.py
MysqlXingnengDiaoyouYuJiagoushejiJesselzj/file.epub
MysqlXingnengDiaoyouYuJiagoushejiJesselzj/index.html
MysqlXingnengDiaoyouYuJiagoushejiJesselzj/css/__init__.py
MysqlXingnengDiaoyouYuJiagoushejiJesselzj/css/annotations.css
MysqlXingnengDiaoyouYuJiagoushejiJesselzj/css/main.css
MysqlXingnengDiaoyouYuJiagoushejiJesselzj/css/normalize.css
MysqlXingnengDiaoyouYuJiagoushejiJesselzj/css/popup.css
MysqlXingnengDiaoyouYuJiagoushejiJesselzj/font/__init__.py
MysqlXingnengDiaoyouYuJiagoushejiJesselzj/font/fontello.eot
MysqlXingnengDiaoyouYuJiagoushejiJesselzj/font/fontello.svg
MysqlXingnengDiaoyouYuJiagoushejiJesselzj/font/fontello.ttf
MysqlXingnengDiaoyouYuJiagoushejiJesselzj/font/fontello.woff
MysqlXingnengDiaoyouYuJiagoushejiJesselzj/img/__init__.py
MysqlXingnengDiaoyouYuJiagoushejiJesselzj/img/annotator-glyph-sprite.png
MysqlXingnengDiaoyouYuJiagoushejiJesselzj/img/annotator-icon-sprite.png
MysqlXingnengDiaoyouYuJiagoushejiJesselzj/img/apple-touch-icon.png
MysqlXingnengDiaoyouYuJiagoushejiJesselzj/img/cancelfullscreen.png
MysqlXingnengDiaoyouYuJiagoushejiJesselzj/img/close.png
MysqlXingnengDiaoyouYuJiagoushejiJesselzj/img/fullscreen.png
MysqlXingnengDiaoyouYuJiagoushejiJesselzj/img/loader.gif
MysqlXingnengDiaoyouYuJiagoushejiJesselzj/img/menu-icon.png
MysqlXingnengDiaoyouYuJiagoushejiJesselzj/img/save.png
MysqlXingnengDiaoyouYuJiagoushejiJesselzj/img/saved.png
MysqlXingnengDiaoyouYuJiagoushejiJesselzj/img/settings-s.png
MysqlXingnengDiaoyouYuJiagoushejiJesselzj/img/settings.png
MysqlXingnengDiaoyouYuJiagoushejiJesselzj/img/star.png
MysqlXingnengDiaoyouYuJiagoushejiJesselzj/js/__init__.py
MysqlXingnengDiaoyouYuJiagoushejiJesselzj/js/epub.js
MysqlXingnengDiaoyouYuJiagoushejiJesselzj/js/epub.min.js
MysqlXingnengDiaoyouYuJiagoushejiJesselzj/js/epub.min.map
MysqlXingnengDiaoyouYuJiagoushejiJesselzj/js/hooks.min.js
mysql_xingneng_diaoyou_yu_jiagousheji_jesselzj-2024.3.2.0.dist-info/METADATA
mysql_xingneng_diaoyou_yu_jiagousheji_jesselzj-2024.3.2.0.dist-info/WHEEL
mysql_xingneng_diaoyou_yu_jiagousheji_jesselzj-2024.3.2.0.dist-info/entry_points.txt
mysql_xingneng_diaoyou_yu_jiagousheji_jesselzj-2024.3.2.0.dist-info/top_level.txt
mysql_xingneng_diaoyou_yu_jiagousheji_jesselzj-2024.3.2.0.dist-info/RECORD
